cfflatten/__init__.py
cfflatten/cf_dns.py
cfflatten/cf_spf_flat.py
cfflatten-22.2.11.data/scripts/cfflatten
cfflatten-22.2.11.dist-info/LICENSE.txt
cfflatten-22.2.11.dist-info/METADATA
cfflatten-22.2.11.dist-info/WHEEL
cfflatten-22.2.11.dist-info/top_level.txt
cfflatten-22.2.11.dist-info/RECORD
