Metadata-Version: 2.1
Name: cfflatten
Version: 22.2.11
Summary: Flatten and Create SPF records in CloudFlare zones
Home-page: https://github.com/Glocktober/cfflatten
Author: gunville
Author-email: rk13088@yahoo.com
License: UNKNOWN
Project-URL: repo, https://github.com/Glocktober/cfflatten.git
Project-URL: overview, https://github.com/Glocktober/cfflatten/blob/main/README.md
Keywords: 'spf cloudflare'
Platform: UNKNOWN
Classifier: Programming Language :: Python :: 3
Classifier: License :: OSI Approved :: MIT License
Classifier: Operating System :: OS Independent
Requires-Python: >=3.7
License-File: LICENSE.txt
Requires-Dist: cloudflare (>=2.8.15)
Requires-Dist: sender-policy-flattener (>=0.3.1)
